rickquests/__init__.py
rickquests/request_util.py
rickquests-3.1.0.dist-info/METADATA
rickquests-3.1.0.dist-info/WHEEL
rickquests-3.1.0.dist-info/top_level.txt
rickquests-3.1.0.dist-info/RECORD
